mlem/__init__.py
mlem/_mlem_version.py
mlem/config.py
mlem/constants.py
mlem/ext.py
mlem/log.py
mlem/telemetry.py
mlem/ui.py
mlem/version.py
mlem/api/__init__.py
mlem/api/commands.py
mlem/api/migrations.py
mlem/api/utils.py
mlem/cli/__init__.py
mlem/cli/apply.py
mlem/cli/build.py
mlem/cli/checkenv.py
mlem/cli/clone.py
mlem/cli/config.py
mlem/cli/declare.py
mlem/cli/deployment.py
mlem/cli/dev.py
mlem/cli/import_object.py
mlem/cli/info.py
mlem/cli/init.py
mlem/cli/link.py
mlem/cli/main.py
mlem/cli/migrate.py
mlem/cli/serve.py
mlem/cli/types.py
mlem/cli/utils.py
mlem/contrib/__init__.py
mlem/contrib/bitbucketfs.py
mlem/contrib/callable.py
mlem/contrib/catboost.py
mlem/contrib/dvc.py
mlem/contrib/fastapi.py
mlem/contrib/git.py
mlem/contrib/github.py
mlem/contrib/gitlabfs.py
mlem/contrib/lightgbm.py
mlem/contrib/numpy.py
mlem/contrib/onnx.py
mlem/contrib/pandas.py
mlem/contrib/pil.py
mlem/contrib/prometheus.py
mlem/contrib/rabbitmq.py
mlem/contrib/requirements.py
mlem/contrib/scipy.py
mlem/contrib/sklearn.py
mlem/contrib/tensorflow.py
mlem/contrib/torch.py
mlem/contrib/torchvision.py
mlem/contrib/venv.py
mlem/contrib/xgboost.py
mlem/contrib/docker/__init__.py
mlem/contrib/docker/base.py
mlem/contrib/docker/context.py
mlem/contrib/docker/copy.j2
mlem/contrib/docker/dockerfile.j2
mlem/contrib/docker/helpers.py
mlem/contrib/docker/install_req.j2
mlem/contrib/docker/utils.py
mlem/contrib/flyio/__init__.py
mlem/contrib/flyio/meta.py
mlem/contrib/flyio/utils.py
mlem/contrib/heroku/__init__.py
mlem/contrib/heroku/build.py
mlem/contrib/heroku/config.py
mlem/contrib/heroku/meta.py
mlem/contrib/heroku/server.py
mlem/contrib/heroku/utils.py
mlem/contrib/kubernetes/__init__.py
mlem/contrib/kubernetes/base.py
mlem/contrib/kubernetes/build.py
mlem/contrib/kubernetes/context.py
mlem/contrib/kubernetes/resources.yaml.j2
mlem/contrib/kubernetes/service.py
mlem/contrib/kubernetes/utils.py
mlem/contrib/pip/__init__.py
mlem/contrib/pip/base.py
mlem/contrib/pip/setup.py.j2
mlem-0.4.14.dist-info/LICENSE
mlem-0.4.14.dist-info/METADATA
mlem-0.4.14.dist-info/WHEEL
mlem-0.4.14.dist-info/entry_points.txt
mlem-0.4.14.dist-info/top_level.txt
mlem-0.4.14.dist-info/RECORD
