Metadata-Version: 2.1
Name: mlem
Version: 0.4.14
Summary: Version and deploy your models following GitOps principles
Home-page: https://mlem.ai
Download-URL: https://github.com/iterative/mlem
Author: Mikhail Sveshnikov
Author-email: mike0sv@iterative.ai
Maintainer: Iterative
Maintainer-email: support@mlem.ai
License: Apache License 2.0
Keywords: data-science data-version-control machine-learning git mlops developer-tools reproducibility collaboration ai
Classifier: Development Status :: 4 - Beta
Classifier: Programming Language :: Python :: 3
Classifier: Programming Language :: Python :: 3.8
Classifier: Programming Language :: Python :: 3.9
Classifier: Programming Language :: Python :: 3.10
Requires-Python: >=3.6
License-File: LICENSE
Requires-Dist: cloudpickle
Requires-Dist: dill
Requires-Dist: requests
Requires-Dist: isort (>=5.10)
Requires-Dist: pydantic (<2,>=1.9.0)
Requires-Dist: typer
Requires-Dist: click (<8.2)
Requires-Dist: rich
Requires-Dist: aiohttp (<4)
Requires-Dist: aiohttp-swagger (<2)
Requires-Dist: Jinja2 (>=3)
Requires-Dist: fsspec (>=2021.7.0)
Requires-Dist: pyparsing (<4)
Requires-Dist: cached-property
Requires-Dist: entrypoints
Requires-Dist: gitpython
Requires-Dist: python-gitlab
Requires-Dist: flatdict
Requires-Dist: iterative-telemetry (>=0.0.6)
Requires-Dist: python-multipart
Requires-Dist: importlib-metadata
Provides-Extra: all
Requires-Dist: pytest ; extra == 'all'
Requires-Dist: pytest-cov ; extra == 'all'
Requires-Dist: pytest-lazy-fixture (==0.6.3) ; extra == 'all'
Requires-Dist: pytest-mock ; extra == 'all'
Requires-Dist: pylint (<2.14) ; extra == 'all'
Requires-Dist: pylint-pytest ; extra == 'all'
Requires-Dist: pylint-plugin-utils ; extra == 'all'
Requires-Dist: flaky ; extra == 'all'
Requires-Dist: s3fs ; extra == 'all'
Requires-Dist: boto3 ; extra == 'all'
Requires-Dist: botocore ; extra == 'all'
Requires-Dist: adlfs ; extra == 'all'
Requires-Dist: gcsfs ; extra == 'all'
Requires-Dist: testcontainers ; extra == 'all'
Requires-Dist: emoji ; extra == 'all'
Requires-Dist: lxml ; extra == 'all'
Requires-Dist: openpyxl ; extra == 'all'
Requires-Dist: xlrd ; extra == 'all'
Requires-Dist: tables ; extra == 'all'
Requires-Dist: pyarrow ; extra == 'all'
Requires-Dist: skl2onnx ; extra == 'all'
Requires-Dist: dvc[s3] ; extra == 'all'
Requires-Dist: httpx ; extra == 'all'
Requires-Dist: jupyter ; extra == 'all'
Requires-Dist: nbconvert ; extra == 'all'
Requires-Dist: nbloader ; extra == 'all'
Requires-Dist: pandas ; extra == 'all'
Requires-Dist: numpy ; extra == 'all'
Requires-Dist: scikit-learn ; extra == 'all'
Requires-Dist: scipy ; extra == 'all'
Requires-Dist: onnx ; extra == 'all'
Requires-Dist: protobuf (==3.20.1) ; extra == 'all'
Requires-Dist: onnxruntime (<1.14) ; extra == 'all'
Requires-Dist: catboost ; extra == 'all'
Requires-Dist: xgboost ; extra == 'all'
Requires-Dist: lightgbm ; extra == 'all'
Requires-Dist: uvicorn ; extra == 'all'
Requires-Dist: fastapi ; extra == 'all'
Requires-Dist: prometheus-fastapi-instrumentator ; extra == 'all'
Requires-Dist: streamlit ; extra == 'all'
Requires-Dist: streamlit-pydantic ; extra == 'all'
Requires-Dist: docker ; extra == 'all'
Requires-Dist: sagemaker ; extra == 'all'
Requires-Dist: torch ; extra == 'all'
Requires-Dist: tensorflow ; extra == 'all'
Requires-Dist: adlfs (>=2021.10.0) ; extra == 'all'
Requires-Dist: azure-identity (>=1.4.0) ; extra == 'all'
Requires-Dist: knack ; extra == 'all'
Requires-Dist: gcsfs (>=2021.11.1) ; extra == 'all'
Requires-Dist: pyarrow (>=1) ; extra == 'all'
Requires-Dist: fsspec[arrow] ; extra == 'all'
Requires-Dist: s3fs[boto3] (>=2021.11.1) ; extra == 'all'
Requires-Dist: aiobotocore[boto3] (>2) ; extra == 'all'
Requires-Dist: bcrypt ; extra == 'all'
Requires-Dist: sshfs[bcrypt] (>=2021.11.2) ; extra == 'all'
Requires-Dist: pika ; extra == 'all'
Requires-Dist: kubernetes ; extra == 'all'
Requires-Dist: dvc (~=2.0) ; extra == 'all'
Requires-Dist: pygit2 ; extra == 'all'
Requires-Dist: tomlkit ; extra == 'all'
Requires-Dist: torchvision ; extra == 'all'
Requires-Dist: Pillow ; extra == 'all'
Requires-Dist: dvc[azure] (~=2.0) ; extra == 'all'
Requires-Dist: dvc[gdrive] (~=2.0) ; extra == 'all'
Requires-Dist: dvc[gs] (~=2.0) ; extra == 'all'
Requires-Dist: dvc[hdfs] (~=2.0) ; extra == 'all'
Requires-Dist: dvc[oss] (~=2.0) ; extra == 'all'
Requires-Dist: dvc[s3] (~=2.0) ; extra == 'all'
Requires-Dist: dvc[ssh] (~=2.0) ; extra == 'all'
Requires-Dist: dvc[ssh_gssapi] (~=2.0) ; extra == 'all'
Requires-Dist: dvc[webdav] (~=2.0) ; extra == 'all'
Requires-Dist: dvc[webhdfs] (~=2.0) ; extra == 'all'
Requires-Dist: dvc[webhdfs_kerberos] (~=2.0) ; extra == 'all'
Provides-Extra: azure
Requires-Dist: adlfs (>=2021.10.0) ; extra == 'azure'
Requires-Dist: azure-identity (>=1.4.0) ; extra == 'azure'
Requires-Dist: knack ; extra == 'azure'
Provides-Extra: catboost
Requires-Dist: catboost ; extra == 'catboost'
Provides-Extra: docker
Requires-Dist: docker ; extra == 'docker'
Provides-Extra: dvc
Requires-Dist: dvc (~=2.0) ; extra == 'dvc'
Provides-Extra: dvc-azure
Requires-Dist: dvc[azure] (~=2.0) ; extra == 'dvc-azure'
Provides-Extra: dvc-gdrive
Requires-Dist: dvc[gdrive] (~=2.0) ; extra == 'dvc-gdrive'
Provides-Extra: dvc-gs
Requires-Dist: dvc[gs] (~=2.0) ; extra == 'dvc-gs'
Provides-Extra: dvc-hdfs
Requires-Dist: dvc[hdfs] (~=2.0) ; extra == 'dvc-hdfs'
Provides-Extra: dvc-oss
Requires-Dist: dvc[oss] (~=2.0) ; extra == 'dvc-oss'
Provides-Extra: dvc-s3
Requires-Dist: dvc[s3] (~=2.0) ; extra == 'dvc-s3'
Provides-Extra: dvc-ssh
Requires-Dist: dvc[ssh] (~=2.0) ; extra == 'dvc-ssh'
Provides-Extra: dvc-ssh_gssapi
Requires-Dist: dvc[ssh_gssapi] (~=2.0) ; extra == 'dvc-ssh_gssapi'
Provides-Extra: dvc-webdav
Requires-Dist: dvc[webdav] (~=2.0) ; extra == 'dvc-webdav'
Provides-Extra: dvc-webhdfs
Requires-Dist: dvc[webhdfs] (~=2.0) ; extra == 'dvc-webhdfs'
Provides-Extra: dvc-webhdfs_kerberos
Requires-Dist: dvc[webhdfs_kerberos] (~=2.0) ; extra == 'dvc-webhdfs_kerberos'
Provides-Extra: fastapi
Requires-Dist: uvicorn ; extra == 'fastapi'
Requires-Dist: fastapi ; extra == 'fastapi'
Provides-Extra: flyio
Requires-Dist: docker ; extra == 'flyio'
Requires-Dist: fastapi ; extra == 'flyio'
Requires-Dist: uvicorn ; extra == 'flyio'
Requires-Dist: tomlkit ; extra == 'flyio'
Provides-Extra: git
Requires-Dist: pygit2 ; extra == 'git'
Provides-Extra: gs
Requires-Dist: gcsfs (>=2021.11.1) ; extra == 'gs'
Provides-Extra: hdfs
Requires-Dist: pyarrow (>=1) ; extra == 'hdfs'
Requires-Dist: fsspec[arrow] ; extra == 'hdfs'
Provides-Extra: heroku
Requires-Dist: docker ; extra == 'heroku'
Requires-Dist: fastapi ; extra == 'heroku'
Requires-Dist: uvicorn ; extra == 'heroku'
Provides-Extra: kubernetes
Requires-Dist: docker ; extra == 'kubernetes'
Requires-Dist: kubernetes ; extra == 'kubernetes'
Provides-Extra: lightgbm
Requires-Dist: lightgbm ; extra == 'lightgbm'
Provides-Extra: numpy
Requires-Dist: numpy ; extra == 'numpy'
Provides-Extra: onnx
Requires-Dist: onnx ; extra == 'onnx'
Provides-Extra: onnxruntime
Requires-Dist: protobuf (==3.20.1) ; extra == 'onnxruntime'
Requires-Dist: onnxruntime (<1.14) ; extra == 'onnxruntime'
Provides-Extra: pandas
Requires-Dist: pandas ; extra == 'pandas'
Provides-Extra: pil
Requires-Dist: Pillow ; extra == 'pil'
Requires-Dist: numpy ; extra == 'pil'
Provides-Extra: prometheus
Requires-Dist: prometheus-fastapi-instrumentator ; extra == 'prometheus'
Provides-Extra: rmq
Requires-Dist: pika ; extra == 'rmq'
Provides-Extra: s3
Requires-Dist: s3fs[boto3] (>=2021.11.1) ; extra == 's3'
Requires-Dist: aiobotocore[boto3] (>2) ; extra == 's3'
Provides-Extra: sagemaker
Requires-Dist: docker ; extra == 'sagemaker'
Requires-Dist: boto3 ; extra == 'sagemaker'
Requires-Dist: sagemaker ; extra == 'sagemaker'
Provides-Extra: scipy
Requires-Dist: scipy ; extra == 'scipy'
Provides-Extra: sklearn
Requires-Dist: scikit-learn ; extra == 'sklearn'
Provides-Extra: ssh
Requires-Dist: bcrypt ; extra == 'ssh'
Requires-Dist: sshfs[bcrypt] (>=2021.11.2) ; extra == 'ssh'
Provides-Extra: streamlit
Requires-Dist: uvicorn ; extra == 'streamlit'
Requires-Dist: fastapi ; extra == 'streamlit'
Requires-Dist: streamlit ; extra == 'streamlit'
Requires-Dist: streamlit-pydantic ; extra == 'streamlit'
Provides-Extra: tensorflow
Requires-Dist: tensorflow ; extra == 'tensorflow'
Provides-Extra: tests
Requires-Dist: pytest ; extra == 'tests'
Requires-Dist: pytest-cov ; extra == 'tests'
Requires-Dist: pytest-lazy-fixture (==0.6.3) ; extra == 'tests'
Requires-Dist: pytest-mock ; extra == 'tests'
Requires-Dist: pylint (<2.14) ; extra == 'tests'
Requires-Dist: pylint-pytest ; extra == 'tests'
Requires-Dist: pylint-plugin-utils ; extra == 'tests'
Requires-Dist: flaky ; extra == 'tests'
Requires-Dist: s3fs ; extra == 'tests'
Requires-Dist: boto3 ; extra == 'tests'
Requires-Dist: botocore ; extra == 'tests'
Requires-Dist: adlfs ; extra == 'tests'
Requires-Dist: gcsfs ; extra == 'tests'
Requires-Dist: testcontainers ; extra == 'tests'
Requires-Dist: emoji ; extra == 'tests'
Requires-Dist: lxml ; extra == 'tests'
Requires-Dist: openpyxl ; extra == 'tests'
Requires-Dist: xlrd ; extra == 'tests'
Requires-Dist: tables ; extra == 'tests'
Requires-Dist: pyarrow ; extra == 'tests'
Requires-Dist: skl2onnx ; extra == 'tests'
Requires-Dist: dvc[s3] ; extra == 'tests'
Requires-Dist: httpx ; extra == 'tests'
Requires-Dist: jupyter ; extra == 'tests'
Requires-Dist: nbconvert ; extra == 'tests'
Requires-Dist: nbloader ; extra == 'tests'
Requires-Dist: pandas ; extra == 'tests'
Requires-Dist: numpy ; extra == 'tests'
Requires-Dist: scikit-learn ; extra == 'tests'
Requires-Dist: scipy ; extra == 'tests'
Requires-Dist: onnx ; extra == 'tests'
Requires-Dist: protobuf (==3.20.1) ; extra == 'tests'
Requires-Dist: onnxruntime (<1.14) ; extra == 'tests'
Requires-Dist: catboost ; extra == 'tests'
Requires-Dist: xgboost ; extra == 'tests'
Requires-Dist: lightgbm ; extra == 'tests'
Requires-Dist: uvicorn ; extra == 'tests'
Requires-Dist: fastapi ; extra == 'tests'
Requires-Dist: prometheus-fastapi-instrumentator ; extra == 'tests'
Requires-Dist: streamlit ; extra == 'tests'
Requires-Dist: streamlit-pydantic ; extra == 'tests'
Requires-Dist: docker ; extra == 'tests'
Requires-Dist: sagemaker ; extra == 'tests'
Requires-Dist: torch ; extra == 'tests'
Requires-Dist: tensorflow ; extra == 'tests'
Requires-Dist: adlfs (>=2021.10.0) ; extra == 'tests'
Requires-Dist: azure-identity (>=1.4.0) ; extra == 'tests'
Requires-Dist: knack ; extra == 'tests'
Requires-Dist: gcsfs (>=2021.11.1) ; extra == 'tests'
Requires-Dist: pyarrow (>=1) ; extra == 'tests'
Requires-Dist: fsspec[arrow] ; extra == 'tests'
Requires-Dist: s3fs[boto3] (>=2021.11.1) ; extra == 'tests'
Requires-Dist: aiobotocore[boto3] (>2) ; extra == 'tests'
Requires-Dist: bcrypt ; extra == 'tests'
Requires-Dist: sshfs[bcrypt] (>=2021.11.2) ; extra == 'tests'
Requires-Dist: pika ; extra == 'tests'
Requires-Dist: kubernetes ; extra == 'tests'
Requires-Dist: dvc (~=2.0) ; extra == 'tests'
Requires-Dist: pygit2 ; extra == 'tests'
Requires-Dist: tomlkit ; extra == 'tests'
Requires-Dist: torchvision ; extra == 'tests'
Requires-Dist: Pillow ; extra == 'tests'
Provides-Extra: torch
Requires-Dist: torch ; extra == 'torch'
Provides-Extra: torchvision
Requires-Dist: torchvision ; extra == 'torchvision'
Provides-Extra: xgboost
Requires-Dist: xgboost ; extra == 'xgboost'
